PythonOpencvLantuChuyiFix1/README.md
PythonOpencvLantuChuyiFix1/__init__.py
PythonOpencvLantuChuyiFix1/__main__.py
PythonOpencvLantuChuyiFix1/file.epub
PythonOpencvLantuChuyiFix1/index.html
PythonOpencvLantuChuyiFix1/css/__init__.py
PythonOpencvLantuChuyiFix1/css/annotations.css
PythonOpencvLantuChuyiFix1/css/main.css
PythonOpencvLantuChuyiFix1/css/normalize.css
PythonOpencvLantuChuyiFix1/css/popup.css
PythonOpencvLantuChuyiFix1/font/__init__.py
PythonOpencvLantuChuyiFix1/font/fontello.eot
PythonOpencvLantuChuyiFix1/font/fontello.svg
PythonOpencvLantuChuyiFix1/font/fontello.ttf
PythonOpencvLantuChuyiFix1/font/fontello.woff
PythonOpencvLantuChuyiFix1/img/__init__.py
PythonOpencvLantuChuyiFix1/img/annotator-glyph-sprite.png
PythonOpencvLantuChuyiFix1/img/annotator-icon-sprite.png
PythonOpencvLantuChuyiFix1/img/apple-touch-icon.png
PythonOpencvLantuChuyiFix1/img/cancelfullscreen.png
PythonOpencvLantuChuyiFix1/img/close.png
PythonOpencvLantuChuyiFix1/img/fullscreen.png
PythonOpencvLantuChuyiFix1/img/loader.gif
PythonOpencvLantuChuyiFix1/img/menu-icon.png
PythonOpencvLantuChuyiFix1/img/save.png
PythonOpencvLantuChuyiFix1/img/saved.png
PythonOpencvLantuChuyiFix1/img/settings-s.png
PythonOpencvLantuChuyiFix1/img/settings.png
PythonOpencvLantuChuyiFix1/img/star.png
PythonOpencvLantuChuyiFix1/js/__init__.py
PythonOpencvLantuChuyiFix1/js/epub.js
PythonOpencvLantuChuyiFix1/js/epub.min.js
PythonOpencvLantuChuyiFix1/js/epub.min.map
PythonOpencvLantuChuyiFix1/js/hooks.min.js
PythonOpencvLantuChuyiFix1/js/hooks.min.map
PythonOpencvLantuChuyiFix1/js/reader.js
PythonOpencvLantuChuyiFix1/js/reader.js.map
PythonOpencvLantuChuyiFix1/js/reader.min.js
PythonOpencvLantuChuyiFix1/js/reader.min.map
PythonOpencvLantuChuyiFix1/js/hooks/__init__.py
PythonOpencvLantuChuyiFix1/js/hooks/extensions/__init__.py
PythonOpencvLantuChuyiFix1/js/hooks/extensions/highlight.js
PythonOpencvLantuChuyiFix1/js/libs/__init__.py
PythonOpencvLantuChuyiFix1/js/libs/jquery.min.js
python_opencv_lantu_chuyi_fix1-2025.3.25.0.dist-info/METADATA
python_opencv_lantu_chuyi_fix1-2025.3.25.0.dist-info/WHEEL
python_opencv_lantu_chuyi_fix1-2025.3.25.0.dist-info/entry_points.txt
python_opencv_lantu_chuyi_fix1-2025.3.25.0.dist-info/top_level.txt
python_opencv_lantu_chuyi_fix1-2025.3.25.0.dist-info/RECORD
